LICENSE
MANIFEST.in
README.rst
setup.py
bsct/__init__.py
bsct/models.py
bsct/urls.py
bsct/views.py
bsct/templates/bsct/base.html
bsct/templates/bsct/plain/confirm_delete.html
bsct/templates/bsct/plain/detail.html
bsct/templates/bsct/plain/form.html
bsct/templates/bsct/plain/list.html
bsct/templates/bsct/plain/paginator.html
bsct/templatetags/__init__.py
bsct/templatetags/bscttags.py
django_bootstrap_crud_templates.egg-info/PKG-INFO
django_bootstrap_crud_templates.egg-info/SOURCES.txt
django_bootstrap_crud_templates.egg-info/dependency_links.txt
django_bootstrap_crud_templates.egg-info/top_level.txt