Metadata-Version: 1.1
Name: django-bootstrap-crud-templates
Version: 1.0.24
Summary: A repository of Bootstrap CRUD templates for Django.
Home-page: http://packages.python.org/django-bootstrap-crud-templates
Author: Z. Alem
Author-email: alem@cidola.com
License: GNU General Public License v3 (GPLv3)
Keywords: django,templates. bootstrap,bootstrap templates,crud templates
Platform: UNKNOWN
Classifier: Environment :: Web Environment
Classifier: Framework :: Django
Classifier: Intended Audience :: Developers
Classifier: License :: OSI Approved :: GNU General Public License v3 (GPLv3)
Classifier: Operating System :: OS Independent
Classifier: Programming Language :: Python
Classifier: Programming Language :: Python :: 2.7
Classifier: Topic :: Internet :: WWW/HTTP
Classifier: Topic :: Internet :: WWW/HTTP :: Dynamic Content
